keyof/__init__.py
keyof/compat.py
keyof/mypy_plugin.py
keyof/py.typed
keyof-0.4.0.dist-info/LICENSE
keyof-0.4.0.dist-info/METADATA
keyof-0.4.0.dist-info/WHEEL
keyof-0.4.0.dist-info/RECORD
