Metadata-Version: 2.1
Name: keyof
Version: 0.4.0
Summary: 
Home-page: https://github.com/ViliamV/keyof
License: MIT
Author: Viliam Valent
Author-email: keyof@valent.email
Requires-Python: >=3.11,<4.0
Classifier: License :: OSI Approved :: MIT License
Classifier: Programming Language :: Python :: 3
Classifier: Programming Language :: Python :: 3.11
Project-URL: Repository, https://github.com/ViliamV/keyof
